dash_nivo_charts/DashNivoBar.py
dash_nivo_charts/DashNivoCalendar.py
dash_nivo_charts/DashNivoCharts.py
dash_nivo_charts/DashNivoChartsCalendar.py
dash_nivo_charts/DashNivoPie.py
dash_nivo_charts/__init__.py
dash_nivo_charts/_imports_.py
dash_nivo_charts/async-DashNivoCharts.js
dash_nivo_charts/async-DashNivoCharts.js.map
dash_nivo_charts/dash_nivo_charts.min.js
dash_nivo_charts/dash_nivo_charts.min.js.map
dash_nivo_charts/metadata.json
dash_nivo_charts/package-info.json
dash_nivo_charts-0.0.1.dist-info/LICENSE
dash_nivo_charts-0.0.1.dist-info/METADATA
dash_nivo_charts-0.0.1.dist-info/WHEEL
dash_nivo_charts-0.0.1.dist-info/top_level.txt
dash_nivo_charts-0.0.1.dist-info/RECORD
